get_external_data2/__main__.py
get_external_data2/data_getter.py
get_external_data2/db.py
get_external_data2/models.py
get_external_data2-1.0.2.dist-info/licenses/LICENSE
get_external_data2-1.0.2.dist-info/METADATA
get_external_data2-1.0.2.dist-info/WHEEL
get_external_data2-1.0.2.dist-info/entry_points.txt
get_external_data2-1.0.2.dist-info/top_level.txt
get_external_data2-1.0.2.dist-info/RECORD
