Metadata-Version: 2.4
Name: get-external-data2
Version: 1.0.2
Summary: Downloads and imports shapefiles into OSM database.
Author-email: Alexander Pozlevich <apozlevich@gmail.com>
Classifier: Development Status :: 3 - Alpha
Classifier: Topic :: Scientific/Engineering :: GIS
Classifier: Typing :: Typed
Requires-Python: >=3.12
License-File: LICENSE
Requires-Dist: argcomplete>=3.6.3
Requires-Dist: psycopg>=3.2.11
Requires-Dist: psycopg-binary>=3.2.11
Requires-Dist: pyaml>=25.7.0
Requires-Dist: pydantic>=2.12.3
Requires-Dist: requests>=2.32.5
Requires-Dist: tqdm-loggable>=0.2
Provides-Extra: dev
Requires-Dist: ruff; extra == "dev"
Dynamic: license-file
